openbiocure_corelib/__init__.py
openbiocure_corelib/__version__.py
openbiocure_corelib/cli.py
openbiocure_corelib-3.1.0.dist-info/licenses/LICENSE
openbiocure_corelib-3.1.0.dist-info/METADATA
openbiocure_corelib-3.1.0.dist-info/WHEEL
openbiocure_corelib-3.1.0.dist-info/top_level.txt
openbiocure_corelib-3.1.0.dist-info/RECORD
