Metadata-Version: 2.4
Name: openbiocure_corelib
Version: 3.1.0
Summary: OpenBioCure_CoreLib is the foundational core library for the HerpAI platform. It provides shared infrastructure components, configuration management, logging utilities, database session handling, and the repository pattern used across HerpAI agents and services.
Author-email: OpenBioCure Contributors <openbiocure@gmail.com>
License: MIT
Requires-Python: >=3.9
License-File: LICENSE
Requires-Dist: sqlalchemy>=2.0.0
Requires-Dist: pyyaml>=6.0
Requires-Dist: aiosqlite>=0.17.0
Requires-Dist: greenlet>=2.0.0
Provides-Extra: dev
Requires-Dist: pytest>=7.0.0; extra == "dev"
Requires-Dist: pytest-asyncio>=0.18.0; extra == "dev"
Requires-Dist: pytest-cov>=4.0.0; extra == "dev"
Requires-Dist: black; extra == "dev"
Requires-Dist: isort; extra == "dev"
Requires-Dist: mypy; extra == "dev"
Requires-Dist: flake8>=7.0.0; extra == "dev"
Requires-Dist: pre-commit; extra == "dev"
Dynamic: license-file
